dynsimf/__init__.py
dynsimf/examples/HIOM.py
dynsimf/examples/Ishigami_sa.py
dynsimf/examples/SIR_ODE.py
dynsimf/examples/SIR_probability.py
dynsimf/examples/__init__.py
dynsimf/examples/black_pete.py
dynsimf/examples/black_pete_dynamic.py
dynsimf/examples/black_pete_dynamic_new_I.py
dynsimf/examples/black_pete_dynamic_normalized.py
dynsimf/examples/black_pete_dynamic_unlinked.py
dynsimf/examples/craving_vs_self_control.py
dynsimf/examples/edge_values_example.py
dynsimf/examples/property_example.py
dynsimf/examples/run_examples.py
dynsimf/examples/run_sa.py
dynsimf/examples/school_segregation.py
dynsimf/examples/utility_cost_example.py
dynsimf/models/Example.py
dynsimf/models/ExampleRunner.py
dynsimf/models/Model.py
dynsimf/models/UtilityCostModel.py
dynsimf/models/__init__.py
dynsimf/models/components/Memory.py
dynsimf/models/components/PropertyFunction.py
dynsimf/models/components/Scheme.py
dynsimf/models/components/Update.py
dynsimf/models/components/__init__.py
dynsimf/models/components/conditions/Condition.py
dynsimf/models/components/conditions/CustomCondition.py
dynsimf/models/components/conditions/StochasticCondition.py
dynsimf/models/components/conditions/ThresholdCondition.py
dynsimf/models/components/conditions/__init__.py
dynsimf/models/helpers/ConfigValidator.py
dynsimf/models/helpers/__init__.py
dynsimf/models/tools/SA.py
dynsimf/models/tools/Visualizer.py
dynsimf/models/tools/__init__.py
dynsimf-0.30.dist-info/LICENSE
dynsimf-0.30.dist-info/METADATA
dynsimf-0.30.dist-info/WHEEL
dynsimf-0.30.dist-info/top_level.txt
dynsimf-0.30.dist-info/RECORD
