Metadata-Version: 2.1
Name: dynsimf
Version: 0.30
Summary: Dynamic Network Simulation Framework
Home-page: https://github.com/Tensaiz/DyNSimF
Author: Mathijs Maijer
Author-email: m.f.maijer@gmail.com
License: BSD-Clause-2
Keywords: dynamic-networks networks simulator network-of-networks analysis
Platform: UNKNOWN
Classifier: Development Status :: 3 - Alpha
Classifier: Intended Audience :: Developers
Classifier: Topic :: Software Development :: Build Tools
Classifier: License :: OSI Approved :: BSD License
Classifier: Operating System :: OS Independent
Classifier: Programming Language :: Python :: 3
License-File: LICENSE
Requires-Dist: numpy
Requires-Dist: networkx
Requires-Dist: tqdm
Requires-Dist: pyintergraph
Requires-Dist: python-igraph
Requires-Dist: pillow
Requires-Dist: sphinx-rtd-theme
Requires-Dist: pytest
Requires-Dist: salib
Requires-Dist: matplotlib
